fuzzy_sql/__init__.py
fuzzy_sql/generate.py
fuzzy_sql/load.py
fuzzy_sql/randomquery.py
fuzzy_sql/report.py
fuzzy_sql-2.0.5.dist-info/LICENSE
fuzzy_sql-2.0.5.dist-info/METADATA
fuzzy_sql-2.0.5.dist-info/WHEEL
fuzzy_sql-2.0.5.dist-info/top_level.txt
fuzzy_sql-2.0.5.dist-info/RECORD
