Metadata-Version: 2.1
Name: fuzzy-sql
Version: 2.0.5
Summary: A generator of random SQL SELECT queries mainly to compare responses from a real dataset against that from a synthetic dataset.
Author: Samer Kababji
Author-email: skababji@ehealthinformation.ca
Project-URL: Home, https://github.com/skababji-ehil/fuzzy_sql
Project-URL: Documentation, https://fuzzy-sql.readthedocs.io/en/latest/index.html#
Keywords: sql,synthetic,clinical trials,generative,testing,fuzzy,fuzzing
Classifier: Development Status :: 4 - Beta
Classifier: Programming Language :: Python :: 3.8
Classifier: Operating System :: OS Independent
Classifier: License :: OSI Approved :: MIT License
License-File: LICENSE
Requires-Dist: pandas
Requires-Dist: Jinja2
Requires-Dist: seaborn
Requires-Dist: scikit-learn
Requires-Dist: jupyter
Requires-Dist: jsonschema
Requires-Dist: multiprocess
Requires-Dist: scipy
Requires-Dist: matplotlib
Provides-Extra: dev
Requires-Dist: wheel ; extra == 'dev'
Requires-Dist: dvc ; extra == 'dev'
Requires-Dist: sphinx ; extra == 'dev'
Requires-Dist: sphinxcontrib-bibtex ; extra == 'dev'
Requires-Dist: sphinxcontrib-napoleon ; extra == 'dev'
